python_project_manager/__init__.py
python_project_manager/config.py
python_project_manager/main.py
python_project_manager/security.py
python_project_manager/utils.py
python_project_manager/templates/gitignore.template
hodlon_python_project_manager-1.0.0.dist-info/LICENSE
hodlon_python_project_manager-1.0.0.dist-info/METADATA
hodlon_python_project_manager-1.0.0.dist-info/WHEEL
hodlon_python_project_manager-1.0.0.dist-info/entry_points.txt
hodlon_python_project_manager-1.0.0.dist-info/top_level.txt
hodlon_python_project_manager-1.0.0.dist-info/RECORD
