Metadata-Version: 2.1
Name: hodlon-python-project-manager
Version: 1.0.0
Summary: A utility tool for Python project initialization and management
Author: HodlON Sàrl
License: Copyright (C) 2024 HodlON Sàrl
Project-URL: Repository, https://github.com/HodlON42/python-project-manager
Project-URL: Documentation, https://github.com/HodlON42/python-project-manager#readme
Project-URL: Bug Tracker, https://github.com/HodlON42/python-project-manager/issues
Classifier: Development Status :: 5 - Production/Stable
Classifier: Environment :: Console
Classifier: Intended Audience :: Developers
Classifier: Topic :: Software Development :: Build Tools
Classifier: Programming Language :: Python :: 3
Classifier: Programming Language :: Python :: 3.8
Classifier: Programming Language :: Python :: 3.9
Classifier: Programming Language :: Python :: 3.10
Classifier: Programming Language :: Python :: 3.11
Requires-Python: >=3.8
License-File: LICENSE
Provides-Extra: test
Requires-Dist: pytest>=7.4.0; extra == "test"
Requires-Dist: pytest-cov>=4.1.0; extra == "test"
